harborscalesdk/__init__.py
harborscalesdk/client.py
harborscalesdk/models.py
harborscalesdk-0.1.9.dist-info/licenses/LICENSE
harborscalesdk-0.1.9.dist-info/METADATA
harborscalesdk-0.1.9.dist-info/WHEEL
harborscalesdk-0.1.9.dist-info/top_level.txt
harborscalesdk-0.1.9.dist-info/RECORD
