Metadata-Version: 2.4
Name: harborscalesdk
Version: 0.1.9
Summary: A Python SDK for interacting with Harbor Scale ingestion endpoints.
Author-email: Harbor Scale <support@harborscale.com>
License:                                  Apache License
Project-URL: Homepage, https://github.com/harborscale/harbor-sdk-python
Project-URL: Bug Tracker, https://github.com/harborscale/harbor-sdk-python/issues
Keywords: sdk,api,telemetry,harbor
Classifier: Development Status :: 4 - Beta
Classifier: Programming Language :: Python :: 3
Classifier: License :: OSI Approved :: MIT License
Classifier: Operating System :: OS Independent
Classifier: Intended Audience :: Developers
Classifier: Topic :: Software Development :: Libraries :: Python Modules
Requires-Python: >=3.8
License-File: LICENSE
Requires-Dist: requests
Requires-Dist: pydantic
Dynamic: license-file
